ganttchart/__init__.py
ganttchart/ganttchart.py
ganttchart-0.3.2.dist-info/METADATA
ganttchart-0.3.2.dist-info/WHEEL
ganttchart-0.3.2.dist-info/top_level.txt
ganttchart-0.3.2.dist-info/RECORD
