Metadata-Version: 2.1
Name: ganttchart
Version: 0.3.2
Summary: ganttchart , a chart for gantt
Home-page: https://github.com/aaly/ganttchart
Author: AbdAllah Aly
Author-email: aaly90@gmail.com
License: UNKNOWN
Platform: UNKNOWN
Classifier: Programming Language :: Python :: 3
Classifier: License :: OSI Approved :: MIT License
Classifier: Operating System :: OS Independent
Requires-Dist: matplotlib
